clrs/__init__.py
clrs/clrs_test.py
clrs/models.py
clrs/py.typed
clrs/_src/__init__.py
clrs/_src/baselines.py
clrs/_src/baselines_test.py
clrs/_src/dataset.py
clrs/_src/dataset_test.py
clrs/_src/decoders.py
clrs/_src/decoders_test.py
clrs/_src/encoders.py
clrs/_src/evaluation.py
clrs/_src/evaluation_test.py
clrs/_src/losses.py
clrs/_src/losses_test.py
clrs/_src/model.py
clrs/_src/nets.py
clrs/_src/probing.py
clrs/_src/probing_test.py
clrs/_src/processors.py
clrs/_src/processors_test.py
clrs/_src/samplers.py
clrs/_src/samplers_test.py
clrs/_src/specs.py
clrs/_src/algorithms/__init__.py
clrs/_src/algorithms/divide_and_conquer.py
clrs/_src/algorithms/divide_and_conquer_test.py
clrs/_src/algorithms/dynamic_programming.py
clrs/_src/algorithms/dynamic_programming_test.py
clrs/_src/algorithms/geometry.py
clrs/_src/algorithms/geometry_test.py
clrs/_src/algorithms/graphs.py
clrs/_src/algorithms/graphs_test.py
clrs/_src/algorithms/greedy.py
clrs/_src/algorithms/greedy_test.py
clrs/_src/algorithms/searching.py
clrs/_src/algorithms/searching_test.py
clrs/_src/algorithms/sorting.py
clrs/_src/algorithms/sorting_test.py
clrs/_src/algorithms/strings.py
clrs/_src/algorithms/strings_test.py
clrs/_src/clrs_text/__init__.py
clrs/_src/clrs_text/clrs_utils.py
clrs/_src/clrs_text/clrs_utils_test.py
clrs/_src/clrs_text/generate_clrs_text.py
clrs/_src/clrs_text/huggingface_generators.py
clrs/_src/clrs_text/huggingface_generators_test.py
clrs/examples/run.py
dm_clrs-2.0.3.dist-info/LICENSE
dm_clrs-2.0.3.dist-info/METADATA
dm_clrs-2.0.3.dist-info/WHEEL
dm_clrs-2.0.3.dist-info/top_level.txt
dm_clrs-2.0.3.dist-info/RECORD
