Metadata-Version: 2.2
Name: dm-clrs
Version: 2.0.3
Summary: The CLRS Algorithmic Reasoning Benchmark.
Home-page: https://github.com/deepmind/clrs
Author: DeepMind
Author-email: clrs-dev@google.com
License: Apache 2.0
Keywords: python machine learning
Classifier: Development Status :: 4 - Beta
Classifier: Environment :: Console
Classifier: Intended Audience :: Science/Research
Classifier: License :: OSI Approved :: Apache Software License
Classifier: Operating System :: POSIX :: Linux
Classifier: Operating System :: Microsoft :: Windows
Classifier: Operating System :: MacOS :: MacOS X
Classifier: Programming Language :: Python :: 3
Classifier: Programming Language :: Python :: 3.6
Classifier: Programming Language :: Python :: 3.7
Classifier: Topic :: Scientific/Engineering :: Artificial Intelligence
Requires-Python: >=3.6
License-File: LICENSE
Requires-Dist: absl-py>=2.1.0
Requires-Dist: attrs>=24.2.0
Requires-Dist: chex>=0.1.86
Requires-Dist: dm-haiku>=0.0.12
Requires-Dist: jax>=0.4.31
Requires-Dist: jaxlib>=0.4.31
Requires-Dist: ml_collections>=0.1.1
Requires-Dist: numpy>=1.26.4
Requires-Dist: opt-einsum>=3.3.0
Requires-Dist: optax>=0.2.3
Requires-Dist: six>=1.16.0
Requires-Dist: tensorflow>=2.17.0
Requires-Dist: tfds-nightly>=4.9.6.dev202409060044
Requires-Dist: toolz>=0.12.1
Dynamic: author
Dynamic: author-email
Dynamic: classifier
Dynamic: description
Dynamic: description-content-type
Dynamic: home-page
Dynamic: keywords
Dynamic: license
Dynamic: requires-dist
Dynamic: requires-python
Dynamic: summary
